bayesbridge/__init__.py
bayesbridge/bayesbridge.py
bayesbridge/gibbs_util.py
bayesbridge/prior.py
bayesbridge/design_matrix/__init__.py
bayesbridge/design_matrix/abstract_matrix.py
bayesbridge/design_matrix/binary_matvec.py
bayesbridge/design_matrix/dense_matrix.py
bayesbridge/design_matrix/mkl_matvec.py
bayesbridge/design_matrix/sparse_matrix.py
bayesbridge/mcmc_diagnostics/__init__.py
bayesbridge/mcmc_diagnostics/demo_helper.py
bayesbridge/mcmc_diagnostics/setup.py
bayesbridge/mcmc_diagnostics/mcmc_diagnostics/__init__.py
bayesbridge/mcmc_diagnostics/mcmc_diagnostics/ar_model.py
bayesbridge/mcmc_diagnostics/mcmc_diagnostics/cramer_von_mises_test.py
bayesbridge/mcmc_diagnostics/mcmc_diagnostics/effective_sample_size.py
bayesbridge/model/__init__.py
bayesbridge/model/abstract_model.py
bayesbridge/model/cox_model.py
bayesbridge/model/factory.py
bayesbridge/model/linear_model.py
bayesbridge/model/logistic_model.py
bayesbridge/random/__init__.py
bayesbridge/random/random.py
bayesbridge/random/normal/__init__.py
bayesbridge/random/normal/normal.cpython-38-darwin.so
bayesbridge/random/polya_gamma/__init__.py
bayesbridge/random/polya_gamma/polya_gamma.cpython-38-darwin.so
bayesbridge/random/polya_gamma/profile_polyagamma.py
bayesbridge/random/polya_gamma/setup.py
bayesbridge/random/tilted_stable/__init__.py
bayesbridge/random/tilted_stable/setup.py
bayesbridge/random/tilted_stable/tilted_stable.cpython-38-darwin.so
bayesbridge/random/uniform/__init__.py
bayesbridge/random/uniform/uniform.cpython-38-darwin.so
bayesbridge/reg_coef_sampler/__init__.py
bayesbridge/reg_coef_sampler/cg_sampler.py
bayesbridge/reg_coef_sampler/direct_gaussian_sampler.py
bayesbridge/reg_coef_sampler/preconditioner.py
bayesbridge/reg_coef_sampler/reg_coef_posterior_summarizer.py
bayesbridge/reg_coef_sampler/reg_coef_sampler.py
bayesbridge/reg_coef_sampler/hamiltonian_monte_carlo/__init__.py
bayesbridge/reg_coef_sampler/hamiltonian_monte_carlo/derivative_tester.py
bayesbridge-0.2.6.dist-info/METADATA
bayesbridge-0.2.6.dist-info/WHEEL
bayesbridge-0.2.6.dist-info/top_level.txt
bayesbridge-0.2.6.dist-info/RECORD
