Metadata-Version: 2.1
Name: bayesbridge
Version: 0.2.6
Summary: Generates posterior samples under Bayesian sparse regression based on the bridge prior using the CG-accelerated Gibbs sampler of Nishimura et. al. (2018). The linear and logistic model are currently supported.
Home-page: https://github.com/aki-nishimura/bayes-bridge
Author: Akihiko (Aki) Nishimura
Author-email: aki.nishimura@jhu.edu
License: MIT
Requires-Dist: numpy (>=1.19)
Requires-Dist: scipy
Provides-Extra: gpu
Requires-Dist: cupy (>=9.4.0) ; extra == 'gpu'
